storage.py
hcs_storage-1.4.dist-info/METADATA
hcs_storage-1.4.dist-info/WHEEL
hcs_storage-1.4.dist-info/RECORD
