Metadata-Version: 2.1
Name: hcs-storage
Version: 1.4
Summary: a storage class wrapping a dict.
Home-page: https://pypi.org/project/hcs-storage/
License: ISCL
Author: Christer Sjöholm
Author-email: 1357-hcs@users.noreply.gitlab.com
Requires-Python: >=3.12,<4.0
Classifier: Development Status :: 6 - Mature
Classifier: Intended Audience :: Developers
Classifier: License :: OSI Approved :: ISC License (ISCL)
Classifier: License :: Other/Proprietary License
Classifier: Operating System :: OS Independent
Classifier: Programming Language :: Python :: 3
Classifier: Programming Language :: Python :: 3.12
Classifier: Topic :: Software Development :: Libraries :: Python Modules
Project-URL: Repository, https://gitlab.com/hcs/hcs-storage
